atta_openai/__init__.py
atta_openai/_constants.py
atta_openai/_exceptions.py
atta_openai/_llm.py
atta_openai/_shared.py
atta_openai/text_standard.py
atta_openai/text_streaming.py
atta_openai-0.1.0.dist-info/WHEEL
atta_openai-0.1.0.dist-info/METADATA
atta_openai-0.1.0.dist-info/RECORD
